{
  "regions": [
    {
      "id": "1",
      "name": "Баткенская область",
      "code": "03"
    },
    {
      "id": "2",
      "name": "Бишкек",
      "code": "01"
    },
    {
      "id": "3",
      "name": "Джалабадская область",
      "code": "04"
    },
    {
      "id": "4",
      "name": "Иссык-Кульская область",
      "code": "09"
    },
    {
      "id": "5",
      "name": "Нарынская область",
      "code": "05"
    },
    {
      "id": "6",
      "name": "Ош",
      "code": "02"
    },
    {
      "id": "7",
      "name": "Ошская область",
      "code": "06"
    },
    {
      "id": "8",
      "name": "Таласская область",
      "code": "07"
    },
    {
      "id": "9",
      "name": "Чуйская область",
      "code": "08"
    }
  ]
}
